{"air_date":"2022-05-23T00:00:00.0000000Z","episode_number":7,"name":"Plan and Execution","overview":"Jimmy and Kim deal with a last-minute snag. Howard's investigation finally yields results.","id":3641946,"production_code":"","season_number":6,"still_path":"/flVUI98wSTtLmYDCx81gowleQTe.jpg","vote_average":9.585,"vote_count":71,"images":{"stills":[{"aspect_ratio":1.778,"file_path":"/flVUI98wSTtLmYDCx81gowleQTe.jpg","height":1080,"vote_average":7.542,"vote_count":8,"width":1920},{"aspect_ratio":1.776,"file_path":"/fI85Vcab6f8eiwuSkPlHGCSwHP0.jpg","height":1080,"vote_average":3.334,"vote_count":1,"width":1918},{"aspect_ratio":1.778,"file_path":"/jeM1tvWGezK6TVQYV5uOjcHGcsr.jpg","height":2160,"vote_average":2.278,"vote_count":3,"width":3840},{"aspect_ratio":1.778,"file_path":"/rClZuXeD2oXSjt2hsvHsghUPrZG.jpg","height":2160,"vote_average":1.75,"vote_count":6,"width":3840},{"aspect_ratio":1.778,"file_path":"/6MU4DKvfHmqf6Wc7zRjcp6mTQAx.jpg","height":1080,"vote_average":1.75,"vote_count":6,"width":1920},{"aspect_ratio":1.778,"file_path":"/d1Flpv7GBClLoBvfD5ENrgks93A.jpg","height":1080,"vote_average":0,"vote_count":0,"width":1920},{"aspect_ratio":1.778,"file_path":"/9G41k1n5V5umqsxgIJ8s8O5jldz.jpg","height":2160,"vote_average":0,"vote_count":0,"width":3840},{"aspect_ratio":1.778,"file_path":"/6LyuDjUF25URomldgcJmtxAHpLt.jpg","height":1080,"vote_average":0,"vote_count":0,"width":1920}]},"external_ids":{"imdb_id":"tt12187040","tvdb_id":8996835},"credits":{"cast":[{"adult":false,"gender":2,"id":59410,"known_for_department":"Acting","name":"Bob Odenkirk","original_name":"Bob Odenkirk","popularity":23.579,"profile_path":"/rF0Lb6SBhGSTvjRffmlKRSeI3jE.jpg","cast_id":0,"character":"Jimmy McGill","credit_id":"534036420e0a2679ad00036d","order":0},{"adult":false,"gender":2,"id":783,"known_for_department":"Acting","name":"Jonathan Banks","original_name":"Jonathan Banks","popularity":38.586,"profile_path":"/bswk26L13PvY4iMTwUTAsepXCLv.jpg","cast_id":0,"character":"Mike Ehrmantraut","credit_id":"5453dcdb0e0a2648d9001cde","order":1},{"adult":false,"gender":1,"id":62765,"known_for_department":"Acting","name":"Rhea Seehorn","original_name":"Rhea Seehorn","popularity":18.935,"profile_path":"/g6niUzFMQOiAcSThWoGk0LlAQRP.jpg","cast_id":0,"character":"Kim Wexler","credit_id":"5472fa25c3a3683703000472","order":3},{"adult":false,"gender":2,"id":76855,"known_for_department":"Acting","name":"Tony Dalton","original_name":"Tony Dalton","popularity":31.135,"profile_path":"/vWteTJu9Dyrax7gQq8ndTjx5s6V.jpg","cast_id":0,"character":"Lalo Salamanca","credit_id":"5e73e152cabfe400181ca842","order":6},{"adult":false,"gender":2,"id":4808,"known_for_department":"Acting","name":"Giancarlo Esposito","original_name":"Giancarlo Esposito","popularity":27.793,"profile_path":"/rcXnr82TwDzU4ZGdBeNXfG0ZQnZ.jpg","cast_id":0,"character":"Gus Fring","credit_id":"6264fbd10b5fd60f77f3246b","order":7}],"crew":[{"adult":false,"gender":2,"id":103009,"known_for_department":"Writing","name":"Thomas Schnauz","original_name":"Thomas Schnauz","popularity":5.081,"profile_path":"/uMz5wsgv6QQAgFI809SgCCbwYn9.jpg","credit_id":"553821d7c3a36831dd005cf3","department":"Directing","job":"Director"},{"adult":false,"gender":2,"id":103009,"known_for_department":"Writing","name":"Thomas Schnauz","original_name":"Thomas Schnauz","popularity":5.081,"profile_path":"/uMz5wsgv6QQAgFI809SgCCbwYn9.jpg","credit_id":"56c4e793c3a3680d54000922","department":"Writing","job":"Writer"},{"adult":false,"gender":2,"id":1543194,"known_for_department":"Camera","name":"Marshall Adams","original_name":"Marshall Adams","popularity":3.565,"profile_path":"/ncUZjPfQrKBdUZV0fOlUwn984rx.jpg","credit_id":"62f67a1d5c564e007ba0882e","department":"Camera","job":"Director of Photography"},{"adult":false,"gender":2,"id":1123195,"known_for_department":"Editing","name":"Skip Macdonald","original_name":"Skip Macdonald","popularity":9.089,"profile_path":"/58Ol4VqSnD8NIp9kpi4NkFEh9RF.jpg","credit_id":"6449044549756004badf436a","department":"Editing","job":"Editor"}],"guest_stars":[{"id":58791,"name":"Patrick Fabian","credit_id":"5472fa49c3a3682c55000ac3","character":"Howard Hamlin","order":4,"profile_path":"/bbsYGlnvGUTTExcabKL1OIhcKyZ.jpg"},{"id":3500324,"name":"Sam Li","credit_id":"628c9d4e1a324817973b8288","character":"Cary","order":1075,"profile_path":"/bHslVd2iqiDeqR5oiUnEqhoFerb.jpg"},{"id":2379636,"name":"Jennifer Yun","credit_id":"628c9db59a64350065b09ade","character":"Daniela","order":1076},{"id":2186193,"name":"Sabrina Stewart","credit_id":"628c9df8d48cee2cbfc852a0","character":"Edwina","order":1077,"profile_path":"/svvxAyTK5ibpYF3UAzzBQJL3Ags.jpg"},{"id":1354265,"name":"Breezy Sharp","credit_id":"628c9e120b7316009e38c279","character":"Casa Tranquila Nurse","order":1078},{"id":111385,"name":"Rachelle Carson","credit_id":"628c9e32d3d3870052792b9f","character":"Charity Executive Director","order":1079,"profile_path":"/dkutbHw1jh0JCj6LZbrjMTNRqHG.jpg"},{"id":3388061,"name":"Amy Puente","credit_id":"628c9e85df86a800a6fecd91","character":"Reporter","order":1080,"profile_path":"/lyo1Dy7lgRdRV7DUsm5wIvE0wcM.jpg"},{"id":2147454,"name":"Alaina Garland","credit_id":"628c9e931a32481799ec77ff","character":"Frustrated Student","order":1081,"profile_path":"/6cd78GUk3qW8FYLCQAi2ffeydCe.jpg"},{"id":3561904,"name":"Micah Cole Reeves","credit_id":"628c9eaa0b7316006614100e","character":"Laundry Worker","order":1082},{"id":159334,"name":"Ray Campbell","credit_id":"5991e7349251410448001228","character":"Tyrus Kitt","order":1085,"profile_path":"/nbapP8LvO1KZrmlpNWthEP40H75.jpg"},{"id":42157,"name":"Ed Begley Jr.","credit_id":"56c4e634925141245100091e","character":"Clifford Main","order":1095,"profile_path":"/cdS6hZVabhpQ3UdIK0HNvYXj5IM.jpg"},{"id":118937,"name":"Dennis Boutsikaris","credit_id":"5e73e398a055ef0012290b8d","character":"Rich Schweikart","order":1099,"profile_path":"/eholEaSnVKzse1l7ph6hDsfTTi7.jpg"},{"id":1173,"name":"Mark Margolis","credit_id":"626500a41f33190065bfbf6b","character":"Hector Salamanca","order":1102,"profile_path":"/rT5TYJIPLBkTqsrUs00AixGeaMM.jpg"},{"id":205209,"name":"Josh Fadem","credit_id":"5991e8aec3a368238200135a","character":"Camera Guy","order":1105,"profile_path":"/3sONgBD0lkO3rRMaTopHW0ZZTkY.jpg"},{"id":1077843,"name":"Geoffrey Pomeroy","credit_id":"628c9d92d3d387006864e3f0","character":"Phil Jergens","order":1106,"profile_path":"/ySOiWeNOquDGC78xNbjCqsN933p.jpg"},{"id":92754,"name":"Marty Lindsey","credit_id":"62cdba37e8131d1dc9f37773","character":"Alvin Reese","order":1108,"profile_path":"/7kOsq1QpMIudPZp6UVweXBfveCE.jpg"},{"id":1569001,"name":"Jessie Ennis","credit_id":"56c4e6e0925141245800092d","character":"Erin Brill","order":1110,"profile_path":"/Rx6zznL7EVBuOueSPfsuPlPvun.jpg"},{"id":1843906,"name":"Julian Bonfiglio","credit_id":"595a55d4c3a368265d03c3be","character":"Sound Guy","order":1111,"profile_path":"/ofrSnfnpSfXjYplqxXdDSrN7nnK.jpg"},{"id":965884,"name":"Hayley Holmes","credit_id":"5991e888925141046a0012fb","character":"Make-Up Girl","order":1112,"profile_path":"/6xrFu7EpgXI8XV5XlD3EyAHD7pu.jpg"},{"id":78602,"name":"Jean Effron","credit_id":"625d2336bf09d100507b7c00","character":"Irene Landry","order":1114,"profile_path":"/htL5hKeqy5SisADbrfJwAZ1LPVx.jpg"},{"id":1370862,"name":"Audrey Moore","credit_id":"625d329768ff70169d4d9dd7","character":"Julie","order":1115,"profile_path":"/wRcOvYHIJghibfUfFZ18D8sjOkc.jpg"},{"id":61115,"name":"John Ennis","credit_id":"62833fa8dcf875334dd23a43","character":"Lenny","order":1116,"profile_path":"/xWbZVmk6hwrSl2NfRNTm7XJphRo.jpg"},{"id":44060,"name":"John Posey","credit_id":"628340aa6d9fe8006803a976","character":"Rand Casimiro","order":1117,"profile_path":"/sUk2tKOWTAkYAxMZ0QfhxdzboJf.jpg"},{"id":42200,"name":"Lennie Loftin","credit_id":"628c9cae9a64350050998bcc","character":"Genidowski","order":1118,"profile_path":"/tLCt8LjeumrCQvQfkrEbg7OQd4B.jpg"}]},"videos":{"results":[{"id":"661b1d367ecd28017c4bc188","iso_639_1":"en","iso_3166_1":"US","key":"5ZdLVrW8RWY","name":"Lalo Comes Back From The Dead - Plan And Execution","site":"YouTube","size":"1080","type":"Clip"},{"id":"65fa1dfd26dac1018713e4f3","iso_639_1":"en","iso_3166_1":"US","key":"i_NB9j4axxk","name":"The Can Trick - Plan And Execution","site":"YouTube","size":"1080","type":"Clip"},{"id":"65ebcb515be00e017d963501","iso_639_1":"en","iso_3166_1":"US","key":"jr66YfNJ7Jg","name":"Saul Improvises A New Scheme - Plan And Execution","site":"YouTube","size":"1080","type":"Clip"},{"id":"65ebcbcdb7d352012ee4a36c","iso_639_1":"en","iso_3166_1":"US","key":"gmPJUCkyRPg","name":"Directing A Fake Bribe - Plan And Execution","site":"YouTube","size":"1080","type":"Clip"},{"id":"65bc730311c0660162d073a2","iso_639_1":"en","iso_3166_1":"US","key":"QI0-d3cCaj4","name":"Howard Falls Into Saul's Trap - Plan And Execution","site":"YouTube","size":"1080","type":"Clip"},{"id":"657be9dde93e9521900e27e5","iso_639_1":"en","iso_3166_1":"US","key":"jPgV1-eNu0c","name":"Lalo Lives In The Sewers - Plan And Execution","site":"YouTube","size":"1080","type":"Clip"},{"id":"64a45de6da10f000e2250833","iso_639_1":"en","iso_3166_1":"US","key":"gSANa2J_Jhw","name":"Howard's Very Last Speech - Plan And Execution","site":"YouTube","size":"1080","type":"Clip"},{"id":"630007881c6aa7007a00420c","iso_639_1":"en","iso_3166_1":"US","key":"p8mb_jO-H2I","name":"The Beginning of the End","site":"YouTube","size":"1080","type":"Clip"}]}}